gh_manager/__init__.py
gh_manager/delete_repo.py
gh_manager/github_token_manager.py
gh_manager/org_username_add.py
gh_manager/repo_file_add.py
gh_manager/repo_file_update.py
gh_manager-0.1.0.dist-info/LICENSE
gh_manager-0.1.0.dist-info/METADATA
gh_manager-0.1.0.dist-info/WHEEL
gh_manager-0.1.0.dist-info/entry_points.txt
gh_manager-0.1.0.dist-info/top_level.txt
gh_manager-0.1.0.dist-info/RECORD
